autoarm/__init__.py
autoarm/association_rules.py
autoarm/dataset.py
autoarm/frequent_itemsets.py
autoarm/recommender.py
tests/__init__.py
tests/test_association_rules.py
tests/test_dataset.py
tests/test_frequent_itemsets.py
tests/test_recommender.py
autoarm-0.1.0.dist-info/LICENSE
autoarm-0.1.0.dist-info/METADATA
autoarm-0.1.0.dist-info/WHEEL
autoarm-0.1.0.dist-info/top_level.txt
autoarm-0.1.0.dist-info/RECORD
