Metadata-Version: 2.1
Name: autoarm
Version: 0.1.0
Summary: AutoARM simplifies and automates association rule mining and related tasks.
Home-page: https://github.com/daikikatsuragawa/autoarm
Author: Daiki Katsuragawa
Author-email: daikikatsuragawa@gmail.com
License: Apache-2.0
Platform: UNKNOWN
Classifier: Programming Language :: Python :: 3
Classifier: License :: OSI Approved :: Apache Software License
Classifier: Operating System :: OS Independent
Requires-Python: >=3.7
Requires-Dist: pandas
Requires-Dist: mlxtend
Requires-Dist: numpy
Requires-Dist: df4loop
